{"name":"The user needs to create a new list in TMDB","id":"list;the-user-needs-to-create-a-new-list-in-tmdb","testSteps":[{"number":1,"description":"Given The user has a valid session created with its API Key","duration":5065,"startTime":"2020-02-27T21:14:41.542135200-05:00[America/Bogota]","result":"SUCCESS","precondition":false,"level":0},{"number":2,"description":"Given A new list needs to be created in TMDB","duration":61420,"startTime":"2020-02-27T21:14:46.612155700-05:00[America/Bogota]","result":"SUCCESS","precondition":false,"level":0},{"number":3,"description":"When The user send a request to create the list","duration":1,"startTime":"2020-02-27T21:15:48.033513900-05:00[America/Bogota]","result":"SUCCESS","precondition":false,"level":0},{"number":4,"description":"Then The service responds with a status code \"200\"","duration":7,"startTime":"2020-02-27T21:15:48.036505-05:00[America/Bogota]","result":"PENDING","precondition":false,"level":0},{"number":5,"description":"And The response contains the new list","duration":1,"startTime":"2020-02-27T21:15:48.045481-05:00[America/Bogota]","result":"IGNORED","precondition":false,"level":0}],"userStory":{"id":"list","storyName":"List","path":"src/test/resources/features/List.feature","type":"feature"},"featureTag":{"name":"Features/List","type":"feature"},"title":"The user needs to create a new list in TMDB","backgroundTitle":"Valid session created","backgroundDescription":"","tags":[{"name":"List","type":"feature"}],"startTime":"2020-02-27T21:14:41.079054900-05:00[America/Bogota]","duration":66971,"projectKey":"","annotatedResult":"PENDING","manual":false,"testSource":"Cucumber","result":"PENDING"}